LICENSE
MANIFEST.in
README.md
setup.py
tox.ini
swing/__init__.py
swing/__main__.py
swing/api.py
swing/builder.py
swing/cli.py
swing/core.py
swing/errors.py
swing/helpers.py
swing/parsers.py
swing/views.py
swing_cli.egg-info/PKG-INFO
swing_cli.egg-info/SOURCES.txt
swing_cli.egg-info/dependency_links.txt
swing_cli.egg-info/entry_points.txt
swing_cli.egg-info/not-zip-safe
swing_cli.egg-info/requires.txt
swing_cli.egg-info/top_level.txt