Metadata-Version: 2.1
Name: swing-cli
Version: 0.1
Summary: Client tool for creating compounded Docker Swarm deployments
Home-page: https://github.com/docker-swing/swing
Author: Jan Šafařík
Author-email: cowjen01@gmail.com
License: Apache License 2.0
Keywords: docker,swarm,repository
Platform: UNKNOWN
Classifier: Intended Audience :: Developers
Classifier: License :: OSI Approved :: Apache Software License
Classifier: Operating System :: POSIX :: Linux
Classifier: Operating System :: MacOS
Classifier: Programming Language :: Python
Classifier: Programming Language :: Python :: 3
Classifier: Programming Language :: Python :: 3.6
Classifier: Programming Language :: Python :: 3.7
